wx4/__init__.py
wx4/anti_detection.py
wx4/utils.py
wx4/wx4.py
wx4-0.1.1.dist-info/METADATA
wx4-0.1.1.dist-info/WHEEL
wx4-0.1.1.dist-info/top_level.txt
wx4-0.1.1.dist-info/RECORD
