Metadata-Version: 2.4
Name: wx4
Version: 0.1.1
Summary: Add your description here
Requires-Python: >=3.13
Requires-Dist: loguru>=0.7.3
Requires-Dist: pillow>=11.1.0
Requires-Dist: pyautogui>=0.9.54
Requires-Dist: pyperclip>=1.9.0
Requires-Dist: uiautomation>=2.0.28
